{
	"confOf#Trip": [
		[
			"Trip",
			"is parent of",
			"Social event"
		],
		[
			"Social event",
			"is child of",
			"Banquet"
		],
		[
			"Social event",
			"is child of",
			"Reception"
		],
		[
			"Reception",
			"is parent of",
			"Social event"
		],
		[
			"Banquet",
			"is parent of",
			"Social event"
		]
	],
	"confOf#Banquet": [
		[
			"Banquet",
			"is parent of",
			"Social event"
		],
		[
			"Social event",
			"has title",
			"Thing"
		],
		[
			"Social event",
			"is child of",
			"Trip"
		],
		[
			"Trip",
			"is parent of",
			"Social event"
		]
	],
	"confOf#Reception": [
		[
			"Reception",
			"is parent of",
			"Social event"
		],
		[
			"Social event",
			"is child of",
			"Banquet"
		],
		[
			"Social event",
			"is parent of",
			"Event"
		],
		[
			"Event",
			"is child of",
			"Administrative event"
		],
		[
			"Event",
			"is child of",
			"Social event"
		],
		[
			"Banquet",
			"is parent of",
			"Social event"
		],
		[
			"Administrative event",
			"is child of",
			"Reviewing event"
		],
		[
			"Administrative event",
			"is parent of",
			"Event"
		]
	],
	"confOf#Social_event": [
		[
			"Social event",
			"is child of",
			"Trip"
		],
		[
			"Social event",
			"is parent of",
			"Event"
		],
		[
			"Event",
			"is child of",
			"Social event"
		],
		[
			"Event",
			"is child of",
			"Administrative event"
		],
		[
			"Trip",
			"is parent of",
			"Social event"
		],
		[
			"Administrative event",
			"is parent of",
			"Event"
		]
	],
	"confOf#Event": [
		[
			"Event",
			"is child of",
			"Social event"
		],
		[
			"Event",
			"is child of",
			"Administrative event"
		],
		[
			"Administrative event",
			"is child of",
			"Reviewing event"
		],
		[
			"Administrative event",
			"parallel with",
			"Administrative event"
		],
		[
			"Social event",
			"is child of",
			"Reception"
		],
		[
			"Social event",
			"is child of",
			"Banquet"
		],
		[
			"Reviewing event",
			"is parent of",
			"Administrative event"
		],
		[
			"Banquet",
			"is parent of",
			"Social event"
		],
		[
			"Reception",
			"is parent of",
			"Social event"
		]
	],
	"confOf#Contribution": [
		[
			"Contribution",
			"is child of",
			"Poster"
		],
		[
			"Contribution",
			"hasKeyword",
			"Thing"
		],
		[
			"Poster",
			"is parent of",
			"Contribution"
		]
	],
	"confOf#City": [],
	"confOf#Organization": [
		[
			"Organization",
			"is child of",
			"Company"
		],
		[
			"Organization",
			"is child of",
			"University"
		],
		[
			"Company",
			"is parent of",
			"Organization"
		],
		[
			"University",
			"is parent of",
			"Organization"
		]
	],
	"confOf#Person": [
		[
			"Person",
			"is parent of",
			"Thing"
		]
	],
	"confOf#Topic": [],
	"confOf#Country": [],
	"confOf#Company": [
		[
			"Company",
			"is parent of",
			"Organization"
		],
		[
			"Organization",
			"is child of",
			"Company"
		],
		[
			"Organization",
			"is child of",
			"University"
		],
		[
			"University",
			"is parent of",
			"Organization"
		]
	],
	"confOf#University": [
		[
			"University",
			"is parent of",
			"Organization"
		],
		[
			"Organization",
			"is child of",
			"Company"
		],
		[
			"Organization",
			"is child of",
			"University"
		],
		[
			"Company",
			"is parent of",
			"Organization"
		]
	],
	"confOf#Scholar": [
		[
			"Scholar",
			"is parent of",
			"Person"
		],
		[
			"Person",
			"hasFirstName",
			"Thing"
		],
		[
			"Person",
			"is parent of",
			"Thing"
		]
	],
	"confOf#Administrator": [
		[
			"Administrator",
			"is parent of",
			"Person"
		],
		[
			"Person",
			"is child of",
			"Scholar"
		],
		[
			"Person",
			"is child of",
			"Member PC"
		],
		[
			"Member PC",
			"expertOn",
			"Topic"
		],
		[
			"Member PC",
			"reviewes",
			"Contribution"
		],
		[
			"Scholar",
			"is parent of",
			"Person"
		],
		[
			"Contribution",
			"contactEmail",
			"Thing"
		],
		[
			"Contribution",
			"is child of",
			"Paper"
		]
	],
	"confOf#Poster": [
		[
			"Poster",
			"is parent of",
			"Contribution"
		],
		[
			"Contribution",
			"is child of",
			"Paper"
		],
		[
			"Contribution",
			"is parent of",
			"Thing"
		],
		[
			"Paper",
			"is parent of",
			"Contribution"
		]
	],
	"confOf#Paper": [
		[
			"Paper",
			"is parent of",
			"Contribution"
		],
		[
			"Contribution",
			"is parent of",
			"Thing"
		]
	],
	"confOf#Short_paper": [
		[
			"Short paper",
			"is parent of",
			"Contribution"
		],
		[
			"Contribution",
			"is child of",
			"Poster"
		],
		[
			"Contribution",
			"is parent of",
			"Thing"
		],
		[
			"Poster",
			"is parent of",
			"Contribution"
		]
	],
	"confOf#Reviewing_results_event": [
		[
			"Reviewing results event",
			"is parent of",
			"Administrative event"
		],
		[
			"Administrative event",
			"is child of",
			"Reviewing results event"
		],
		[
			"Administrative event",
			"is parent of",
			"Event"
		],
		[
			"Event",
			"is child of",
			"Working event"
		],
		[
			"Event",
			"is child of",
			"Administrative event"
		],
		[
			"Working event",
			"is child of",
			"Tutorial"
		],
		[
			"Working event",
			"is parent of",
			"Event"
		]
	],
	"confOf#Administrative_event": [
		[
			"Administrative event",
			"parallel with",
			"Administrative event"
		],
		[
			"Administrative event",
			"is parent of",
			"Event"
		],
		[
			"Event",
			"is child of",
			"Working event"
		],
		[
			"Event",
			"is child of",
			"Social event"
		],
		[
			"Social event",
			"has title",
			"Thing"
		],
		[
			"Social event",
			"is child of",
			"Banquet"
		],
		[
			"Working event",
			"is child of",
			"Conference"
		],
		[
			"Working event",
			"hasAdministrativeEvent",
			"Administrative event"
		],
		[
			"Banquet",
			"is parent of",
			"Social event"
		],
		[
			"Conference",
			"is parent of",
			"Working event"
		]
	],
	"confOf#Reviewing_event": [
		[
			"Reviewing event",
			"is parent of",
			"Administrative event"
		],
		[
			"Administrative event",
			"is child of",
			"Reviewing results event"
		],
		[
			"Administrative event",
			"is parent of",
			"Event"
		],
		[
			"Event",
			"is child of",
			"Administrative event"
		],
		[
			"Event",
			"is child of",
			"Social event"
		],
		[
			"Reviewing results event",
			"is parent of",
			"Administrative event"
		],
		[
			"Social event",
			"defaultChoice",
			"Thing"
		],
		[
			"Social event",
			"is child of",
			"Banquet"
		]
	],
	"confOf#Registration_of_participants_event": [
		[
			"Registration of participants event",
			"is parent of",
			"Administrative event"
		],
		[
			"Administrative event",
			"is child of",
			"Reviewing event"
		],
		[
			"Administrative event",
			"is child of",
			"Registration of participants event"
		],
		[
			"Reviewing event",
			"is parent of",
			"Administrative event"
		]
	],
	"confOf#Submission_event": [
		[
			"Submission event",
			"is parent of",
			"Administrative event"
		],
		[
			"Administrative event",
			"is parent of",
			"Event"
		],
		[
			"Event",
			"is child of",
			"Administrative event"
		],
		[
			"Event",
			"is child of",
			"Social event"
		],
		[
			"Social event",
			"defaultChoice",
			"Thing"
		],
		[
			"Social event",
			"is child of",
			"Banquet"
		]
	],
	"confOf#Camera_Ready_event": [
		[
			"Camera Ready event",
			"is parent of",
			"Administrative event"
		],
		[
			"Administrative event",
			"is parent of",
			"Event"
		],
		[
			"Event",
			"is child of",
			"Working event"
		],
		[
			"Event",
			"is child of",
			"Social event"
		],
		[
			"Working event",
			"is parent of",
			"Event"
		],
		[
			"Social event",
			"is child of",
			"Trip"
		],
		[
			"Social event",
			"is parent of",
			"Event"
		]
	],
	"confOf#Workshop": [
		[
			"Workshop",
			"is parent of",
			"Working event"
		],
		[
			"Working event",
			"has title",
			"Thing"
		],
		[
			"Working event",
			"is parent of",
			"Event"
		],
		[
			"Event",
			"is child of",
			"Working event"
		],
		[
			"Event",
			"is child of",
			"Social event"
		],
		[
			"Social event",
			"has title",
			"Thing"
		],
		[
			"Social event",
			"is child of",
			"Banquet"
		]
	],
	"confOf#Conference": [
		[
			"Conference",
			"is parent of",
			"Working event"
		],
		[
			"Working event",
			"is child of",
			"Conference"
		],
		[
			"Working event",
			"is parent of",
			"Event"
		],
		[
			"Event",
			"is child of",
			"Working event"
		],
		[
			"Event",
			"is child of",
			"Social event"
		],
		[
			"Social event",
			"is child of",
			"Banquet"
		],
		[
			"Social event",
			"is child of",
			"Reception"
		]
	],
	"confOf#Tutorial": [
		[
			"Tutorial",
			"is parent of",
			"Working event"
		],
		[
			"Working event",
			"defaultChoice",
			"Thing"
		],
		[
			"Working event",
			"hasAdministrativeEvent",
			"Administrative event"
		],
		[
			"Administrative event",
			"is child of",
			"Reviewing results event"
		],
		[
			"Administrative event",
			"is parent of",
			"Event"
		],
		[
			"Event",
			"is child of",
			"Working event"
		],
		[
			"Event",
			"is child of",
			"Social event"
		],
		[
			"Reviewing results event",
			"is parent of",
			"Administrative event"
		]
	],
	"confOf#Working_event": [
		[
			"Working event",
			"is child of",
			"Conference"
		],
		[
			"Working event",
			"defaultChoice",
			"Thing"
		],
		[
			"Conference",
			"is parent of",
			"Working event"
		]
	],
	"confOf#Member": [
		[
			"Member",
			"is parent of",
			"Participant"
		],
		[
			"Participant",
			"is parent of",
			"Person"
		],
		[
			"Person",
			"is child of",
			"Assistant"
		],
		[
			"Person",
			"is child of",
			"Science Worker"
		],
		[
			"Science Worker",
			"is parent of",
			"Person"
		],
		[
			"Assistant",
			"is parent of",
			"Person"
		]
	],
	"confOf#Participant": [
		[
			"Participant",
			"is child of",
			"Regular"
		],
		[
			"Participant",
			"is parent of",
			"Person"
		],
		[
			"Person",
			"hasSurname",
			"Thing"
		],
		[
			"Person",
			"is parent of",
			"Thing"
		],
		[
			"Regular",
			"is parent of",
			"Participant"
		]
	],
	"confOf#Member_PC": [
		[
			"Member PC",
			"is parent of",
			"Person"
		],
		[
			"Member PC",
			"expertOn",
			"Topic"
		],
		[
			"Person",
			"hasFirstName",
			"Thing"
		],
		[
			"Person",
			"is parent of",
			"Thing"
		]
	],
	"confOf#Chair_PC": [
		[
			"Chair PC",
			"is parent of",
			"Person"
		],
		[
			"Person",
			"is parent of",
			"Thing"
		],
		[
			"Person",
			"is child of",
			"Administrator"
		],
		[
			"Administrator",
			"is parent of",
			"Person"
		]
	],
	"confOf#Student": [
		[
			"Student",
			"is parent of",
			"Participant"
		],
		[
			"Participant",
			"is parent of",
			"Person"
		],
		[
			"Participant",
			"is child of",
			"Student"
		],
		[
			"Person",
			"hasSurname",
			"Thing"
		],
		[
			"Person",
			"is parent of",
			"Thing"
		]
	],
	"confOf#Science_Worker": [
		[
			"Science Worker",
			"is parent of",
			"Person"
		],
		[
			"Person",
			"is child of",
			"Scholar"
		],
		[
			"Person",
			"is parent of",
			"Thing"
		],
		[
			"Scholar",
			"is parent of",
			"Person"
		]
	],
	"confOf#Assistant": [
		[
			"Assistant",
			"is parent of",
			"Person"
		],
		[
			"Person",
			"hasFirstName",
			"Thing"
		],
		[
			"Person",
			"hasEmail",
			"Thing"
		]
	],
	"confOf#Volunteer": [
		[
			"Volunteer",
			"is parent of",
			"Person"
		],
		[
			"Person",
			"is child of",
			"Assistant"
		],
		[
			"Person",
			"is child of",
			"Author"
		],
		[
			"Assistant",
			"is parent of",
			"Person"
		],
		[
			"Author",
			"writes",
			"Contribution"
		],
		[
			"Contribution",
			"is child of",
			"Paper"
		],
		[
			"Contribution",
			"is parent of",
			"Thing"
		]
	],
	"confOf#Regular": [
		[
			"Regular",
			"is parent of",
			"Participant"
		],
		[
			"Participant",
			"is parent of",
			"Person"
		],
		[
			"Participant",
			"is child of",
			"Student"
		],
		[
			"Person",
			"is child of",
			"Scholar"
		],
		[
			"Person",
			"hasCountry",
			"Country"
		],
		[
			"Student",
			"is parent of",
			"Participant"
		],
		[
			"Scholar",
			"is parent of",
			"Person"
		]
	],
	"confOf#Author": [
		[
			"Author",
			"is parent of",
			"Person"
		],
		[
			"Person",
			"is parent of",
			"Thing"
		],
		[
			"Person",
			"is child of",
			"Administrator"
		],
		[
			"Administrator",
			"is parent of",
			"Person"
		]
	]
}